umsgpack.py
umsgpack-0.1.0.dist-info/DESCRIPTION.rst
umsgpack-0.1.0.dist-info/METADATA
umsgpack-0.1.0.dist-info/metadata.json
umsgpack-0.1.0.dist-info/pbr.json
umsgpack-0.1.0.dist-info/RECORD
umsgpack-0.1.0.dist-info/top_level.txt
umsgpack-0.1.0.dist-info/WHEEL
