Metadata-Version: 1.1
Name: umsgpack
Version: 0.1.0
Summary: Unicode-friendly wrapper around msgpack.
Home-page: https://github.com/minrk/umsgpack
Author: Min RK
Author-email: benjaminrk@gmail.com
License: BSD
Platform: UNKNOWN
Classifier: Intended Audience :: Developers
Classifier: Intended Audience :: System Administrators
Classifier: License :: OSI Approved :: BSD License
Classifier: Programming Language :: Python
Classifier: Programming Language :: Python :: 2
Classifier: Programming Language :: Python :: 2.7
Classifier: Programming Language :: Python :: 3
Classifier: Programming Language :: Python :: 3.3
Classifier: Programming Language :: Python :: 3.4
